weathora/__init__.py
weathora/cli.py
weathora/utils.py
weathora-0.0.3.dist-info/METADATA
weathora-0.0.3.dist-info/WHEEL
weathora-0.0.3.dist-info/entry_points.txt
weathora-0.0.3.dist-info/top_level.txt
weathora-0.0.3.dist-info/RECORD
