Metadata-Version: 2.4
Name: weathora
Version: 0.0.3
Summary: A Python CLI tool to fetch live weather data using OpenWeather API
Author: Ishan Bhat
Author-email: ishan2003bhat@gmail.com
Keywords: weather cli python-cli
Classifier: Development Status :: 4 - Beta
Classifier: Intended Audience :: Developers
Classifier: License :: OSI Approved :: MIT License
Classifier: Operating System :: OS Independent
Classifier: Programming Language :: Python :: 3
Classifier: Programming Language :: Python :: 3.6
Classifier: Programming Language :: Python :: 3.7
Classifier: Programming Language :: Python :: 3.8
Classifier: Programming Language :: Python :: 3.9
Classifier: Programming Language :: Python :: 3.10
Classifier: Programming Language :: Python :: 3.11
Classifier: Programming Language :: Python :: 3.12
Requires-Python: >=3.6
Provides-Extra: test
Provides-Extra: dev
Provides-Extra: docs
Provides-Extra: all
Dynamic: author
Dynamic: author-email
Dynamic: classifier
Dynamic: description
Dynamic: description-content-type
Dynamic: keywords
Dynamic: provides-extra
Dynamic: requires-python
Dynamic: summary
